reviewer_stk_ai/__init__.py
reviewer_stk_ai/__main__.py
reviewer_stk_ai/cli.py
reviewer_stk_ai/src/__init__.py
reviewer_stk_ai/src/config/__init__.py
reviewer_stk_ai/src/config/env_config.py
reviewer_stk_ai/src/exceptions/__init__.py
reviewer_stk_ai/src/exceptions/authentication_error.py
reviewer_stk_ai/src/exceptions/integration_contract_error.py
reviewer_stk_ai/src/exceptions/integration_error.py
reviewer_stk_ai/src/exceptions/service_permission_error.py
reviewer_stk_ai/src/models/__init__.py
reviewer_stk_ai/src/models/file_review.py
reviewer_stk_ai/src/service/__init__.py
reviewer_stk_ai/src/service/reviewer_service.py
reviewer_stk_ai/src/service/stk_callback_service.py
reviewer_stk_ai/src/service/stk_execution_service.py
reviewer_stk_ai/src/service/stk_token_service.py
reviewer_stk_ai/src/utils/__init__.py
reviewer_stk_ai/src/utils/constants.py
reviewer_stk_ai/src/utils/file_helper.py
reviewer_stk_ai/src/utils/git_helper.py
reviewer_stk_ai/src/utils/report_helper.py
reviewer_stk_ai-1.1.0.dist-info/entry_points.txt
reviewer_stk_ai-1.1.0.dist-info/LICENSE
reviewer_stk_ai-1.1.0.dist-info/METADATA
reviewer_stk_ai-1.1.0.dist-info/WHEEL
reviewer_stk_ai-1.1.0.dist-info/RECORD
