Metadata-Version: 2.1
Name: reviewer-stk-ai
Version: 1.1.0
Summary: Automated analysis with Stackspot AI offers capabilities such as code review generation, documentation creation, and much more.
Home-page: https://github.com/william1184/content-reviewer-stk-ai-cli
License: MIT
Author: Frank William
Author-email: williamsp1184@gmail.com
Maintainer: Frank William
Maintainer-email: williamsp1184@gmail.com
Requires-Python: >=3.11,<4.0
Classifier: License :: OSI Approved :: MIT License
Classifier: Operating System :: OS Independent
Classifier: Programming Language :: Python :: 3
Classifier: Programming Language :: Python :: 3.11
Classifier: Programming Language :: Python :: 3.12
Requires-Dist: click (>=8.1.7,<9.0.0)
Requires-Dist: gitpython (>=3.1.43,<4.0.0)
Requires-Dist: requests (>=2.32.3,<3.0.0)
Requires-Dist: retrying (>=1.3.4,<2.0.0)
